{"tracks":[{"album":{"album_type":"album","artists":[{"external_urls":{"spotify":"https://open.spotify.com/artist/6DFJfhZxwWe1yKQvRDJmdl"},"href":"https://api.spotify.com/v1/artists/6DFJfhZxwWe1yKQvRDJmdl","id":"6DFJfhZxwWe1yKQvRDJmdl","name":"Hyper","type":"artist","uri":"spotify:artist:6DFJfhZxwWe1yKQvRDJmdl"}],"available_markets":["AD","AE","AG","AL","AM","AO","AR","AT","AU","AZ","BA","BB","BD","BE","BF","BG","BH","BI","BJ","BN","BO","BR","BS","BT","BW","BY","BZ","CA","CH","CI","CL","CM","CO","CR","CV","CW","CY","CZ","DE","DJ","DK","DM","DO","DZ","EC","EE","EG","ES","FI","FJ","FM","FR","GA","GB","GD","GE","GH","GM","GN","GQ","GR","GT","GW","GY","HK","HN","HR","HT","HU","ID","IE","IL","IN","IS","IT","JM","JO","JP","KE","KG","KH","KI","KM","KN","KR","KW","KZ","LA","LB","LC","LI","LK","LR","LS","LT","LU","LV","MA","MC","MD","ME","MG","MH","MK","ML","MN","MO","MR","MT","MU","MV","MW","MX","MY","MZ","NA","NE","NG","NI","NL","NO","NP","NR","NZ","OM","PA","PE","PG","PH","PK","PL","PS","PT","PW","PY","QA","RO","RS","RU","RW","SA","SB","SC","SE","SG","SI","SK","SL","SM","SN","SR","ST","SV","SZ","TD","TG","TH","TL","TN","TO","TR","TT","TV","TW","TZ","UA","UG","US","UY","UZ","VC","VN","VU","WS","XK","ZA","ZM","ZW"],"external_urls":{"spotify":"https://open.spotify.com/album/6uvquJHxA2D9KmHR6oJgXB"},"href":"https://api.spotify.com/v1/albums/6uvquJHxA2D9KmHR6oJgXB","id":"6uvquJHxA2D9KmHR6oJgXB","images":[{"height":640,"url":"https://i.scdn.co/image/ab67616d0000b273b0222d2ff7d5f263639c9548","width":640},{"height":300,"url":"https://i.scdn.co/image/ab67616d00001e02b0222d2ff7d5f263639c9548","width":300},{"height":64,"url":"https://i.scdn.co/image/ab67616d00004851b0222d2ff7d5f263639c9548","width":64}],"name":"Lies","release_date":"2014-01-03","release_date_precision":"day","total_tracks":10,"type":"album","uri":"spotify:album:6uvquJHxA2D9KmHR6oJgXB"},"artists":[{"external_urls":{"spotify":"https://open.spotify.com/artist/6DFJfhZxwWe1yKQvRDJmdl"},"href":"https://api.spotify.com/v1/artists/6DFJfhZxwWe1yKQvRDJmdl","id":"6DFJfhZxwWe1yKQvRDJmdl","name":"Hyper","type":"artist","uri":"spotify:artist:6DFJfhZxwWe1yKQvRDJmdl"}],"available_markets":["AD","AE","AG","AL","AM","AO","AR","AT","AU","AZ","BA","BB","BD","BE","BF","BG","BH","BI","BJ","BN","BO","BR","BS","BT","BW","BY","BZ","CA","CH","CI","CL","CM","CO","CR","CV","CW","CY","CZ","DE","DJ","DK","DM","DO","DZ","EC","EE","EG","ES","FI","FJ","FM","FR","GA","GB","GD","GE","GH","GM","GN","GQ","GR","GT","GW","GY","HK","HN","HR","HT","HU","ID","IE","IL","IN","IS","IT","JM","JO","JP","KE","KG","KH","KI","KM","KN","KR","KW","KZ","LA","LB","LC","LI","LK","LR","LS","LT","LU","LV","MA","MC","MD","ME","MG","MH","MK","ML","MN","MO","MR","MT","MU","MV","MW","MX","MY","MZ","NA","NE","NG","NI","NL","NO","NP","NR","NZ","OM","PA","PE","PG","PH","PK","PL","PS","PT","PW","PY","QA","RO","RS","RU","RW","SA","SB","SC","SE","SG","SI","SK","SL","SM","SN","SR","ST","SV","SZ","TD","TG","TH","TL","TN","TO","TR","TT","TV","TW","TZ","UA","UG","US","UY","UZ","VC","VN","VU","WS","XK","ZA","ZM","ZW"],"disc_number":1,"duration_ms":276000,"episode":false,"explicit":false,"external_ids":{"isrc":"CA5KR1042794"},"external_urls":{"spotify":"https://open.spotify.com/track/4Zl87UYUFG5OJNPhzMTk20"},"href":"https://api.spotify.com/v1/tracks/4Zl87UYUFG5OJNPhzMTk20","id":"4Zl87UYUFG5OJNPhzMTk20","is_local":false,"name":"Clockwork - Original Mix","popularity":54,"preview_url":"https://p.scdn.co/mp3-preview/8f4acc349ce01022d22ec46935ceeef85a9d6bbc?cid=ace5f2d6e3af4a78af05061f9a27201c","track":true,"track_number":1,"type":"track","uri":"spotify:track:4Zl87UYUFG5OJNPhzMTk20"},{"album":{"album_type":"single","artists":[{"external_urls":{"spotify":"https://open.spotify.com/artist/0LgrViZrCyMgg5MfTc33bd"},"href":"https://api.spotify.com/v1/artists/0LgrViZrCyMgg5MfTc33bd","id":"0LgrViZrCyMgg5MfTc33bd","name":"EDDIE","type":"artist","uri":"spotify:artist:0LgrViZrCyMgg5MfTc33bd"}],"available_markets":["AD","AE","AG","AL","AM","AO","AR","AT","AU","AZ","BA","BB","BD","BE","BF","BG","BH","BI","BJ","BN","BO","BR","BS","BT","BW","BY","BZ","CA","CH","CI","CL","CM","CO","CR","CV","CY","CZ","DE","DJ","DK","DM","DO","DZ","EC","EE","EG","ES","FI","FJ","FM","FR","GA","GB","GD","GE","GH","GM","GN","GQ","GR","GT","GW","GY","HK","HN","HR","HT","HU","ID","IE","IL","IN","IS","IT","JM","JO","JP","KE","KG","KH","KI","KM","KN","KR","KW","KZ","LA","LB","LC","LI","LK","LR","LS","LT","LU","LV","MA","MC","MD","ME","MG","MH","MK","ML","MN","MO","MR","MT","MU","MV","MW","MX","MY","MZ","NA","NE","NG","NI","NL","NO","NP","NR","NZ","OM","PA","PE","PG","PH","PK","PL","PS","PT","PW","PY","QA","RO","RS","RU","RW","SA","SB","SC","SE","SG","SI","SK","SL","SM","SN","SR","ST","SV","SZ","TD","TG","TH","TL","TN","TO","TR","TT","TV","TW","TZ","UA","UG","US","UY","UZ","VC","VN","VU","WS","XK","ZA","ZM","ZW"],"external_urls":{"spotify":"https://open.spotify.com/album/5L10rteO7NVH2RbZlUyWGt"},"href":"https://api.spotify.com/v1/albums/5L10rteO7NVH2RbZlUyWGt","id":"5L10rteO7NVH2RbZlUyWGt","images":[{"height":640,"url":"https://i.scdn.co/image/ab67616d0000b273f5a0933e60d1be80fb1b2735","width":640},{"height":300,"url":"https://i.scdn.co/image/ab67616d00001e02f5a0933e60d1be80fb1b2735","width":300},{"height":64,"url":"https://i.scdn.co/image/ab67616d00004851f5a0933e60d1be80fb1b2735","width":64}],"name":"Disembodied","release_date":"2019-05-07","release_date_precision":"day","total_tracks":4,"type":"album","uri":"spotify:album:5L10rteO7NVH2RbZlUyWGt"},"artists":[{"external_urls":{"spotify":"https://open.spotify.com/artist/0LgrViZrCyMgg5MfTc33bd"},"href":"https://api.spotify.com/v1/artists/0LgrViZrCyMgg5MfTc33bd","id":"0LgrViZrCyMgg5MfTc33bd","name":"EDDIE","type":"artist","uri":"spotify:artist:0LgrViZrCyMgg5MfTc33bd"}],"available_markets":["AD","AE","AG","AL","AM","AO","AR","AT","AU","AZ","BA","BB","BD","BE","BF","BG","BH","BI","BJ","BN","BO","BR","BS","BT","BW","BY","BZ","CA","CH","CI","CL","CM","CO","CR","CV","CY","CZ","DE","DJ","DK","DM","DO","DZ","EC","EE","EG","ES","FI","FJ","FM","FR","GA","GB","GD","GE","GH","GM","GN","GQ","GR","GT","GW","GY","HK","HN","HR","HT","HU","ID","IE","IL","IN","IS","IT","JM","JO","JP","KE","KG","KH","KI","KM","KN","KR","KW","KZ","LA","LB","LC","LI","LK","LR","LS","LT","LU","LV","MA","MC","MD","ME","MG","MH","MK","ML","MN","MO","MR","MT","MU","MV","MW","MX","MY","MZ","NA","NE","NG","NI","NL","NO","NP","NR","NZ","OM","PA","PE","PG","PH","PK","PL","PS","PT","PW","PY","QA","RO","RS","RU","RW","SA","SB","SC","SE","SG","SI","SK","SL","SM","SN","SR","ST","SV","SZ","TD","TG","TH","TL","TN","TO","TR","TT","TV","TW","TZ","UA","UG","US","UY","UZ","VC","VN","VU","WS","XK","ZA","ZM","ZW"],"disc_number":1,"duration_ms":330937,"episode":false,"explicit":false,"external_ids":{"isrc":"GBTDG1301736"},"external_urls":{"spotify":"https://open.spotify.com/track/7B25qFeKgDW6X7gDogoseo"},"href":"https://api.spotify.com/v1/tracks/7B25qFeKgDW6X7gDogoseo","id":"7B25qFeKgDW6X7gDogoseo","is_local":false,"name":"Healed","popularity":41,"preview_url":"https://p.scdn.co/mp3-preview/c235ba362c7c8af95415af5d0ab7164f52230aa3?cid=ace5f2d6e3af4a78af05061f9a27201c","track":true,"track_number":1,"type":"track","uri":"spotify:track:7B25qFeKgDW6X7gDogoseo"},{"album":{"album_type":"single","artists":[{"external_urls":{"spotify":"https://open.spotify.com/artist/20yuGdfbRkW0HH3OfG1Nkg"},"href":"https://api.spotify.com/v1/artists/20yuGdfbRkW0HH3OfG1Nkg","id":"20yuGdfbRkW0HH3OfG1Nkg","name":"No Mana","type":"artist","uri":"spotify:artist:20yuGdfbRkW0HH3OfG1Nkg"}],"available_markets":["AD","AE","AG","AL","AM","AO","AR","AT","AU","AZ","BA","BB","BD","BE","BF","BG","BH","BI","BJ","BN","BO","BR","BS","BT","BW","BY","BZ","CA","CH","CI","CL","CM","CO","CR","CV","CW","CY","CZ","DE","DJ","DK","DM","DO","DZ","EC","EE","EG","ES","FI","FJ","FM","FR","GA","GB","GD","GE","GH","GM","GN","GQ","GR","GT","GW","GY","HK","HN","HR","HT","HU","ID","IE","IL","IN","IS","IT","JM","JO","JP","KE","KG","KH","KI","KM","KN","KR","KW","KZ","LA","LB","LC","LI","LK","LR","LS","LT","LU","LV","MA","MC","MD","ME","MG","MH","MK","ML","MN","MO","MR","MT","MU","MV","MW","MX","MY","MZ","NA","NE","NG","NI","NL","NO","NP","NR","NZ","OM","PA","PE","PG","PH","PK","PL","PS","PT","PW","PY","QA","RO","RS","RU","RW","SA","SB","SC","SE","SG","SI","SK","SL","SM","SN","SR","ST","SV","SZ","TD","TG","TH","TL","TN","TO","TR","TT","TV","TW","TZ","UA","UG","US","UY","UZ","VC","VN","VU","WS","XK","ZA","ZM","ZW"],"external_urls":{"spotify":"https://open.spotify.com/album/6UejxB6w9yR4agY4jlx0yV"},"href":"https://api.spotify.com/v1/albums/6UejxB6w9yR4agY4jlx0yV","id":"6UejxB6w9yR4agY4jlx0yV","images":[{"height":640,"url":"https://i.scdn.co/image/ab67616d0000b273906023d2e2a281bfb7e81ba6","width":640},{"height":300,"url":"https://i.scdn.co/image/ab67616d00001e02906023d2e2a281bfb7e81ba6","width":300},{"height":64,"url":"https://i.scdn.co/image/ab67616d00004851906023d2e2a281bfb7e81ba6","width":64}],"name":"The Same Way","release_date":"2020-08-14","release_date_precision":"day","total_tracks":1,"type":"album","uri":"spotify:album:6UejxB6w9yR4agY4jlx0yV"},"artists":[{"external_urls":{"spotify":"https://open.spotify.com/artist/20yuGdfbRkW0HH3OfG1Nkg"},"href":"https://api.spotify.com/v1/artists/20yuGdfbRkW0HH3OfG1Nkg","id":"20yuGdfbRkW0HH3OfG1Nkg","name":"No Mana","type":"artist","uri":"spotify:artist:20yuGdfbRkW0HH3OfG1Nkg"},{"external_urls":{"spotify":"https://open.spotify.com/artist/5DNApAt05XowaylsOJo1eW"},"href":"https://api.spotify.com/v1/artists/5DNApAt05XowaylsOJo1eW","id":"5DNApAt05XowaylsOJo1eW","name":"Voicians","type":"artist","uri":"spotify:artist:5DNApAt05XowaylsOJo1eW"}],"available_markets":["AD","AE","AG","AL","AM","AO","AR","AT","AU","AZ","BA","BB","BD","BE","BF","BG","BH","BI","BJ","BN","BO","BR","BS","BT","BW","BY","BZ","CA","CH","CI","CL","CM","CO","CR","CV","CW","CY","CZ","DE","DJ","DK","DM","DO","DZ","EC","EE","EG","ES","FI","FJ","FM","FR","GA","GB","GD","GE","GH","GM","GN","GQ","GR","GT","GW","GY","HK","HN","HR","HT","HU","ID","IE","IL","IN","IS","IT","JM","JO","JP","KE","KG","KH","KI","KM","KN","KR","KW","KZ","LA","LB","LC","LI","LK","LR","LS","LT","LU","LV","MA","MC","MD","ME","MG","MH","MK","ML","MN","MO","MR","MT","MU","MV","MW","MX","MY","MZ","NA","NE","NG","NI","NL","NO","NP","NR","NZ","OM","PA","PE","PG","PH","PK","PL","PS","PT","PW","PY","QA","RO","RS","RU","RW","SA","SB","SC","SE","SG","SI","SK","SL","SM","SN","SR","ST","SV","SZ","TD","TG","TH","TL","TN","TO","TR","TT","TV","TW","TZ","UA","UG","US","UY","UZ","VC","VN","VU","WS","XK","ZA","ZM","ZW"],"disc_number":1,"duration_ms":281250,"episode":false,"explicit":false,"external_ids":{"isrc":"GBTDG1302067"},"external_urls":{"spotify":"https://open.spotify.com/track/674yKExc1HvFbOzNxoxsnk"},"href":"https://api.spotify.com/v1/tracks/674yKExc1HvFbOzNxoxsnk","id":"674yKExc1HvFbOzNxoxsnk","is_local":false,"name":"The Same Way","popularity":40,"preview_url":"https://p.scdn.co/mp3-preview/2b9b4fe22c71e7c724c16007547f19e75f29d104?cid=ace5f2d6e3af4a78af05061f9a27201c","track":true,"track_number":1,"type":"track","uri":"spotify:track:674yKExc1HvFbOzNxoxsnk"},{"album":{"album_type":"single","artists":[{"external_urls":{"spotify":"https://open.spotify.com/artist/0LgrViZrCyMgg5MfTc33bd"},"href":"https://api.spotify.com/v1/artists/0LgrViZrCyMgg5MfTc33bd","id":"0LgrViZrCyMgg5MfTc33bd","name":"EDDIE","type":"artist","uri":"spotify:artist:0LgrViZrCyMgg5MfTc33bd"}],"available_markets":["AD","AE","AG","AL","AM","AO","AR","AT","AU","AZ","BA","BB","BD","BE","BF","BG","BH","BI","BJ","BN","BO","BR","BS","BT","BW","BY","BZ","CA","CH","CI","CL","CM","CO","CR","CV","CW","CY","CZ","DE","DJ","DK","DM","DO","DZ","EC","EE","EG","ES","FI","FJ","FM","FR","GA","GB","GD","GE","GH","GM","GN","GQ","GR","GT","GW","GY","HK","HN","HR","HT","HU","ID","IE","IL","IN","IS","IT","JM","JO","JP","KE","KG","KH","KI","KM","KN","KR","KW","KZ","LA","LB","LC","LI","LK","LR","LS","LT","LU","LV","MA","MC","MD","ME","MG","MH","MK","ML","MN","MO","MR","MT","MU","MV","MW","MX","MY","MZ","NA","NE","NG","NI","NL","NO","NP","NR","NZ","OM","PA","PE","PG","PH","PK","PL","PS","PT","PW","PY","QA","RO","RS","RU","RW","SA","SB","SC","SE","SG","SI","SK","SL","SM","SN","SR","ST","SV","SZ","TD","TG","TH","TL","TN","TO","TR","TT","TV","TW","TZ","UA","UG","US","UY","UZ","VC","VN","VU","WS","XK","ZA","ZM","ZW"],"external_urls":{"spotify":"https://open.spotify.com/album/39lnrwTl6fnTnOJk4trEdL"},"href":"https://api.spotify.com/v1/albums/39lnrwTl6fnTnOJk4trEdL","id":"39lnrwTl6fnTnOJk4trEdL","images":[{"height":640,"url":"https://i.scdn.co/image/ab67616d0000b27313430d49b9ea1dc05c6edb9d","width":640},{"height":300,"url":"https://i.scdn.co/image/ab67616d00001e0213430d49b9ea1dc05c6edb9d","width":300},{"height":64,"url":"https://i.scdn.co/image/ab67616d0000485113430d49b9ea1dc05c6edb9d","width":64}],"name":"Blueprints","release_date":"2020-10-09","release_date_precision":"day","total_tracks":6,"type":"album","uri":"spotify:album:39lnrwTl6fnTnOJk4trEdL"},"artists":[{"external_urls":{"spotify":"https://open.spotify.com/artist/0LgrViZrCyMgg5MfTc33bd"},"href":"https://api.spotify.com/v1/artists/0LgrViZrCyMgg5MfTc33bd","id":"0LgrViZrCyMgg5MfTc33bd","name":"EDDIE","type":"artist","uri":"spotify:artist:0LgrViZrCyMgg5MfTc33bd"}],"available_markets":["AD","AE","AG","AL","AM","AO","AR","AT","AU","AZ","BA","BB","BD","BE","BF","BG","BH","BI","BJ","BN","BO","BR","BS","BT","BW","BY","BZ","CA","CH","CI","CL","CM","CO","CR","CV","CW","CY","CZ","DE","DJ","DK","DM","DO","DZ","EC","EE","EG","ES","FI","FJ","FM","FR","GA","GB","GD","GE","GH","GM","GN","GQ","GR","GT","GW","GY","HK","HN","HR","HT","HU","ID","IE","IL","IN","IS","IT","JM","JO","JP","KE","KG","KH","KI","KM","KN","KR","KW","KZ","LA","LB","LC","LI","LK","LR","LS","LT","LU","LV","MA","MC","MD","ME","MG","MH","MK","ML","MN","MO","MR","MT","MU","MV","MW","MX","MY","MZ","NA","NE","NG","NI","NL","NO","NP","NR","NZ","OM","PA","PE","PG","PH","PK","PL","PS","PT","PW","PY","QA","RO","RS","RU","RW","SA","SB","SC","SE","SG","SI","SK","SL","SM","SN","SR","ST","SV","SZ","TD","TG","TH","TL","TN","TO","TR","TT","TV","TW","TZ","UA","UG","US","UY","UZ","VC","VN","VU","WS","XK","ZA","ZM","ZW"],"disc_number":1,"duration_ms":255039,"episode":false,"explicit":false,"external_ids":{"isrc":"GBTDG1302098"},"external_urls":{"spotify":"https://open.spotify.com/track/1VUGVnnYeOdvhfH5Bz3wcJ"},"href":"https://api.spotify.com/v1/tracks/1VUGVnnYeOdvhfH5Bz3wcJ","id":"1VUGVnnYeOdvhfH5Bz3wcJ","is_local":false,"name":"The 31-79 Jgb215","popularity":19,"preview_url":"https://p.scdn.co/mp3-preview/95067d43b0c152f7dc0e28177c3005fb4485cac2?cid=ace5f2d6e3af4a78af05061f9a27201c","track":true,"track_number":3,"type":"track","uri":"spotify:track:1VUGVnnYeOdvhfH5Bz3wcJ"},{"album":{"album_type":"single","artists":[{"external_urls":{"spotify":"https://open.spotify.com/artist/0LgrViZrCyMgg5MfTc33bd"},"href":"https://api.spotify.com/v1/artists/0LgrViZrCyMgg5MfTc33bd","id":"0LgrViZrCyMgg5MfTc33bd","name":"EDDIE","type":"artist","uri":"spotify:artist:0LgrViZrCyMgg5MfTc33bd"}],"available_markets":["AD","AE","AG","AL","AM","AO","AR","AT","AU","AZ","BA","BB","BD","BE","BF","BG","BH","BI","BJ","BN","BO","BR","BS","BT","BW","BY","BZ","CA","CH","CI","CL","CM","CO","CR","CV","CW","CY","CZ","DE","DJ","DK","DM","DO","DZ","EC","EE","EG","ES","FI","FJ","FM","FR","GA","GB","GD","GE","GH","GM","GN","GQ","GR","GT","GW","GY","HK","HN","HR","HT","HU","ID","IE","IL","IN","IS","IT","JM","JO","JP","KE","KG","KH","KI","KM","KN","KR","KW","KZ","LA","LB","LC","LI","LK","LR","LS","LT","LU","LV","MA","MC","MD","ME","MG","MH","MK","ML","MN","MO","MR","MT","MU","MV","MW","MX","MY","MZ","NA","NE","NG","NI","NL","NO","NP","NR","NZ","OM","PA","PE","PG","PH","PK","PL","PS","PT","PW","PY","QA","RO","RS","RU","RW","SA","SB","SC","SE","SG","SI","SK","SL","SM","SN","SR","ST","SV","SZ","TD","TG","TH","TL","TN","TO","TR","TT","TV","TW","TZ","UA","UG","US","UY","UZ","VC","VN","VU","WS","XK","ZA","ZM","ZW"],"external_urls":{"spotify":"https://open.spotify.com/album/39lnrwTl6fnTnOJk4trEdL"},"href":"https://api.spotify.com/v1/albums/39lnrwTl6fnTnOJk4trEdL","id":"39lnrwTl6fnTnOJk4trEdL","images":[{"height":640,"url":"https://i.scdn.co/image/ab67616d0000b27313430d49b9ea1dc05c6edb9d","width":640},{"height":300,"url":"https://i.scdn.co/image/ab67616d00001e0213430d49b9ea1dc05c6edb9d","width":300},{"height":64,"url":"https://i.scdn.co/image/ab67616d0000485113430d49b9ea1dc05c6edb9d","width":64}],"name":"Blueprints","release_date":"2020-10-09","release_date_precision":"day","total_tracks":6,"type":"album","uri":"spotify:album:39lnrwTl6fnTnOJk4trEdL"},"artists":[{"external_urls":{"spotify":"https://open.spotify.com/artist/0LgrViZrCyMgg5MfTc33bd"},"href":"https://api.spotify.com/v1/artists/0LgrViZrCyMgg5MfTc33bd","id":"0LgrViZrCyMgg5MfTc33bd","name":"EDDIE","type":"artist","uri":"spotify:artist:0LgrViZrCyMgg5MfTc33bd"}],"available_markets":["AD","AE","AG","AL","AM","AO","AR","AT","AU","AZ","BA","BB","BD","BE","BF","BG","BH","BI","BJ","BN","BO","BR","BS","BT","BW","BY","BZ","CA","CH","CI","CL","CM","CO","CR","CV","CW","CY","CZ","DE","DJ","DK","DM","DO","DZ","EC","EE","EG","ES","FI","FJ","FM","FR","GA","GB","GD","GE","GH","GM","GN","GQ","GR","GT","GW","GY","HK","HN","HR","HT","HU","ID","IE","IL","IN","IS","IT","JM","JO","JP","KE","KG","KH","KI","KM","KN","KR","KW","KZ","LA","LB","LC","LI","LK","LR","LS","LT","LU","LV","MA","MC","MD","ME","MG","MH","MK","ML","MN","MO","MR","MT","MU","MV","MW","MX","MY","MZ","NA","NE","NG","NI","NL","NO","NP","NR","NZ","OM","PA","PE","PG","PH","PK","PL","PS","PT","PW","PY","QA","RO","RS","RU","RW","SA","SB","SC","SE","SG","SI","SK","SL","SM","SN","SR","ST","SV","SZ","TD","TG","TH","TL","TN","TO","TR","TT","TV","TW","TZ","UA","UG","US","UY","UZ","VC","VN","VU","WS","XK","ZA","ZM","ZW"],"disc_number":1,"duration_ms":247301,"episode":false,"explicit":false,"external_ids":{"isrc":"GBTDG1302101"},"external_urls":{"spotify":"https://open.spotify.com/track/7bPMuamCIRuhbGnzJR6T0n"},"href":"https://api.spotify.com/v1/tracks/7bPMuamCIRuhbGnzJR6T0n","id":"7bPMuamCIRuhbGnzJR6T0n","is_local":false,"name":"Lawtons Hammer of Wanderlust","popularity":16,"preview_url":"https://p.scdn.co/mp3-preview/cb5f11b793bcfcae4000bb54e713b9fe1ab05eed?cid=ace5f2d6e3af4a78af05061f9a27201c","track":true,"track_number":6,"type":"track","uri":"spotify:track:7bPMuamCIRuhbGnzJR6T0n"}]}